structure_aram/__init__.py
structure_aram/admin.py
structure_aram/apps.py
structure_aram/cli.py
structure_aram/models.py
structure_aram/tests.py
structure_aram/views.py
structure_aram/migrations/__init__.py
structure_aram-0.1.6.dist-info/METADATA
structure_aram-0.1.6.dist-info/WHEEL
structure_aram-0.1.6.dist-info/entry_points.txt
structure_aram-0.1.6.dist-info/top_level.txt
structure_aram-0.1.6.dist-info/RECORD
